django_tastypie_hmacauth-0.1.dist-info/DESCRIPTION.rst
django_tastypie_hmacauth-0.1.dist-info/METADATA
django_tastypie_hmacauth-0.1.dist-info/RECORD
django_tastypie_hmacauth-0.1.dist-info/WHEEL
django_tastypie_hmacauth-0.1.dist-info/entry_points.txt
django_tastypie_hmacauth-0.1.dist-info/metadata.json
django_tastypie_hmacauth-0.1.dist-info/top_level.txt
tastypie_hmacauth/__init__.py
tastypie_hmacauth/authentication.py
