Metadata-Version: 2.0
Name: django-tastypie-hmacauth
Version: 0.1
Summary: A HMAC class authentication for Tastypie and Django
Home-page: https://github.com/matheuscas/django-tastypie-hmacauth.git
Author: Matheus Cardoso
Author-email: matheus.mcas@gmail.com
License: MIT
Keywords: django tastypie authentication hmac sha256
Platform: UNKNOWN
Classifier: Development Status :: 4 - Beta
Classifier: Intended Audience :: Developers
Classifier: Topic :: Software Development :: Libraries :: Python Modules
Classifier: Topic :: System :: Systems Administration :: Authentication/Directory
Classifier: Environment :: Web Environment
Classifier: Framework :: Django
Classifier: License :: OSI Approved :: MIT License
Classifier: Programming Language :: Python :: 2
Classifier: Programming Language :: Python :: 2.6
Classifier: Programming Language :: Python :: 2.7
Requires-Dist: django-tastypie (>=0.12.1)
Provides-Extra: dev
Requires-Dist: check-manifest; extra == 'dev'
Provides-Extra: test
Requires-Dist: coverage; extra == 'test'
